ngeodesic/__init__.py
ngeodesic/bench/__init__.py
ngeodesic/bench/io.py
ngeodesic/bench/metrics.py
ngeodesic/compat/__init__.py
ngeodesic/compat/types.py
ngeodesic/core/__init__.py
ngeodesic/core/denoise.py
ngeodesic/core/energies.py
ngeodesic/core/funnel_profile.py
ngeodesic/core/matched_filter.py
ngeodesic/core/parser.py
ngeodesic/core/pca_warp.py
ngeodesic/core/smoothing.py
ngeodesic/sidecar/__init__.py
ngeodesic/sidecar/hooks.py
ngeodesic/sidecar/latents.py
ngeodesic/sidecar/runner.py
ngeodesic/stage11/__init__.py
ngeodesic/stage11/guard.py
ngeodesic/stage11/hooks.py
ngeodesic/stage11/runner.py
ngeodesic/synth/__init__.py
ngeodesic/synth/arc_like.py
ngeodesic/viz/__init__.py
ngeodesic/viz/trisurf.py
ngeodesic/viz/well_features.py
ngeodesic/viz/well_render.py
ngeodesic-0.1.0.dist-info/licenses/LICENSE
ngeodesic-0.1.0.dist-info/METADATA
ngeodesic-0.1.0.dist-info/WHEEL
ngeodesic-0.1.0.dist-info/entry_points.txt
ngeodesic-0.1.0.dist-info/top_level.txt
ngeodesic-0.1.0.dist-info/RECORD
