Metadata-Version: 2.4
Name: ngeodesic
Version: 0.1.0
Summary: Geometry-First AI Reasoning Engine
Author: Ian C. Moore
License-Expression: Apache-2.0
Requires-Python: >=3.10
License-File: LICENSE
Requires-Dist: numpy>=1.26
Requires-Dist: typing_extensions>=4.8
Provides-Extra: ml
Requires-Dist: scikit-learn>=1.4; extra == "ml"
Provides-Extra: viz
Requires-Dist: matplotlib>=3.8; extra == "viz"
Requires-Dist: scipy>=1.11; extra == "viz"
Provides-Extra: dev
Requires-Dist: pytest>=8; extra == "dev"
Requires-Dist: pytest-cov>=5; extra == "dev"
Requires-Dist: ruff>=0.5; extra == "dev"
Requires-Dist: mypy>=1.10; extra == "dev"
Dynamic: license-file
